proxifier_cli/__init__.py
proxifier_cli/license.py
proxifier_cli/process.py
proxifier_cli/profile.ppx
proxifier_cli/profiles.py
proxifier_cli-1.0.5.dist-info/METADATA
proxifier_cli-1.0.5.dist-info/WHEEL
proxifier_cli-1.0.5.dist-info/top_level.txt
proxifier_cli-1.0.5.dist-info/RECORD
